vws_cli/__init__.py
vws_cli/_setuptools_scm_version.py
vws_cli/commands.py
vws_cli/py.typed
vws_cli/query.py
vws_cli/options/__init__.py
vws_cli/options/credentials.py
vws_cli/options/targets.py
vws_cli-2026.1.25.1.dist-info/licenses/LICENSE
vws_cli-2026.1.25.1.dist-info/METADATA
vws_cli-2026.1.25.1.dist-info/WHEEL
vws_cli-2026.1.25.1.dist-info/entry_points.txt
vws_cli-2026.1.25.1.dist-info/top_level.txt
vws_cli-2026.1.25.1.dist-info/RECORD
