Metadata-Version: 2.4
Name: vws-cli
Version: 2026.1.25.1
Summary: A CLI for the Vuforia Web Services (VWS) API.
Author-email: Adam Dangoor <adamdangoor@gmail.com>
License-Expression: MIT
Project-URL: Documentation, https://vws-python.github.io/vws-cli/
Project-URL: Source, https://github.com/VWS-Python/vws-cli
Keywords: cli,vuforia,vws
Classifier: Development Status :: 5 - Production/Stable
Classifier: Environment :: Web Environment
Classifier: Operating System :: Microsoft :: Windows
Classifier: Operating System :: POSIX
Classifier: Programming Language :: Python :: 3 :: Only
Classifier: Programming Language :: Python :: 3.13
Requires-Python: >=3.13
License-File: LICENSE
Requires-Dist: beartype==0.22.9
Requires-Dist: click==8.3.1
Requires-Dist: pyyaml==6.0.3
Requires-Dist: vws-python==2025.3.10.1
Provides-Extra: dev
Requires-Dist: actionlint-py==1.7.10.24; extra == "dev"
Requires-Dist: check-manifest==0.51; extra == "dev"
Requires-Dist: deptry==0.24.0; extra == "dev"
Requires-Dist: doc8==2.0.0; extra == "dev"
Requires-Dist: doccmd==2026.1.23.4; extra == "dev"
Requires-Dist: docformatter==1.7.7; extra == "dev"
Requires-Dist: freezegun==1.5.5; extra == "dev"
Requires-Dist: furo==2025.12.19; extra == "dev"
Requires-Dist: hadolint-bin==2.14.0; sys_platform != "win32" and extra == "dev"
Requires-Dist: interrogate==1.7.0; extra == "dev"
Requires-Dist: mypy[faster-cache]==1.19.1; extra == "dev"
Requires-Dist: mypy-strict-kwargs==2026.1.12; extra == "dev"
Requires-Dist: prek==0.3.0; extra == "dev"
Requires-Dist: pylint[spelling]==4.0.4; extra == "dev"
Requires-Dist: pyproject-fmt==2.11.1; extra == "dev"
Requires-Dist: pyrefly==0.49.0; extra == "dev"
Requires-Dist: pyright==1.1.408; extra == "dev"
Requires-Dist: pyroma==5.0.1; extra == "dev"
Requires-Dist: pytest==9.0.2; extra == "dev"
Requires-Dist: pytest-cov==7.0.0; extra == "dev"
Requires-Dist: pytest-regressions==2.9.1; extra == "dev"
Requires-Dist: ruff==0.14.14; extra == "dev"
Requires-Dist: setuptools-scm==9.2.2; extra == "dev"
Requires-Dist: shellcheck-py==0.11.0.1; extra == "dev"
Requires-Dist: shfmt-py==3.12.0.2; extra == "dev"
Requires-Dist: sphinx==9.1.0; extra == "dev"
Requires-Dist: sphinx-click==6.2.0; extra == "dev"
Requires-Dist: sphinx-copybutton==0.5.2; extra == "dev"
Requires-Dist: sphinx-inline-tabs==2025.12.21.14; extra == "dev"
Requires-Dist: sphinx-lint==1.0.2; extra == "dev"
Requires-Dist: sphinx-pyproject==0.3.0; extra == "dev"
Requires-Dist: sphinx-substitution-extensions==2026.1.12; extra == "dev"
Requires-Dist: sphinxcontrib-spelling==8.0.2; extra == "dev"
Requires-Dist: ty==0.0.13; extra == "dev"
Requires-Dist: types-pyyaml==6.0.12.20250915; extra == "dev"
Requires-Dist: vulture==2.14; extra == "dev"
Requires-Dist: vws-python-mock==2025.3.10.1; extra == "dev"
Requires-Dist: vws-test-fixtures==2023.3.5; extra == "dev"
Requires-Dist: yamlfix==1.19.1; extra == "dev"
Requires-Dist: zizmor==1.22.0; extra == "dev"
Provides-Extra: release
Requires-Dist: check-wheel-contents==0.6.3; extra == "release"
Requires-Dist: homebrew-pypi-poet==0.10.0; extra == "release"
Dynamic: license-file
